{"runtime":2679,"energy":{"pkg":196.65887451171875,"pp0":0,"dram":39.468505859375},"perf_counters":{"PERF_COUNT_HW_REF_CPU_CYCLES":0,"PERF_COUNT_HW_BRANCH_INSTRUCTIONS":0,"PERF_COUNT_HW_CACHE_MISSES":0,"PERF_COUNT_HW_INSTRUCTIONS":0,"PERF_COUNT_HW_BRANCH_MISSES":0,"PERF_COUNT_HW_CACHE_REFERENCES":0,"PERF_COUNT_HW_CPU_CYCLES":0}}
{"runtime":2502,"energy":{"pkg":189.9576416015625,"pp0":0,"dram":37.37762451171875},"perf_counters":{"PERF_COUNT_HW_REF_CPU_CYCLES":0,"PERF_COUNT_HW_BRANCH_INSTRUCTIONS":0,"PERF_COUNT_HW_CACHE_MISSES":0,"PERF_COUNT_HW_INSTRUCTIONS":0,"PERF_COUNT_HW_BRANCH_MISSES":0,"PERF_COUNT_HW_CACHE_REFERENCES":0,"PERF_COUNT_HW_CPU_CYCLES":0}}
{"runtime":2658,"energy":{"pkg":195.112548828125,"pp0":0,"dram":38.93988037109375},"perf_counters":{"PERF_COUNT_HW_REF_CPU_CYCLES":0,"PERF_COUNT_HW_BRANCH_INSTRUCTIONS":0,"PERF_COUNT_HW_CACHE_MISSES":0,"PERF_COUNT_HW_INSTRUCTIONS":0,"PERF_COUNT_HW_BRANCH_MISSES":0,"PERF_COUNT_HW_CACHE_REFERENCES":0,"PERF_COUNT_HW_CPU_CYCLES":0}}
{"runtime":2647,"energy":{"pkg":195.7667236328125,"pp0":0,"dram":39.2945556640625},"perf_counters":{"PERF_COUNT_HW_REF_CPU_CYCLES":0,"PERF_COUNT_HW_BRANCH_INSTRUCTIONS":0,"PERF_COUNT_HW_CACHE_MISSES":0,"PERF_COUNT_HW_INSTRUCTIONS":0,"PERF_COUNT_HW_BRANCH_MISSES":0,"PERF_COUNT_HW_CACHE_REFERENCES":0,"PERF_COUNT_HW_CPU_CYCLES":0}}
{"runtime":2605,"energy":{"pkg":193.49609375,"pp0":0,"dram":38.67034912109375},"perf_counters":{"PERF_COUNT_HW_REF_CPU_CYCLES":0,"PERF_COUNT_HW_BRANCH_INSTRUCTIONS":0,"PERF_COUNT_HW_CACHE_MISSES":0,"PERF_COUNT_HW_INSTRUCTIONS":0,"PERF_COUNT_HW_BRANCH_MISSES":0,"PERF_COUNT_HW_CACHE_REFERENCES":0,"PERF_COUNT_HW_CPU_CYCLES":0}}
{"runtime":2670,"energy":{"pkg":196.5435791015625,"pp0":0,"dram":39.6767578125},"perf_counters":{"PERF_COUNT_HW_REF_CPU_CYCLES":0,"PERF_COUNT_HW_BRANCH_INSTRUCTIONS":0,"PERF_COUNT_HW_CACHE_MISSES":0,"PERF_COUNT_HW_INSTRUCTIONS":0,"PERF_COUNT_HW_BRANCH_MISSES":0,"PERF_COUNT_HW_CACHE_REFERENCES":0,"PERF_COUNT_HW_CPU_CYCLES":0}}
{"runtime":2705,"energy":{"pkg":197.572509765625,"pp0":0,"dram":39.70660400390625},"perf_counters":{"PERF_COUNT_HW_REF_CPU_CYCLES":0,"PERF_COUNT_HW_BRANCH_INSTRUCTIONS":0,"PERF_COUNT_HW_CACHE_MISSES":0,"PERF_COUNT_HW_INSTRUCTIONS":0,"PERF_COUNT_HW_BRANCH_MISSES":0,"PERF_COUNT_HW_CACHE_REFERENCES":0,"PERF_COUNT_HW_CPU_CYCLES":0}}
{"runtime":2448,"energy":{"pkg":188.34185791015625,"pp0":0,"dram":37.196533203125},"perf_counters":{"PERF_COUNT_HW_REF_CPU_CYCLES":0,"PERF_COUNT_HW_BRANCH_INSTRUCTIONS":0,"PERF_COUNT_HW_CACHE_MISSES":0,"PERF_COUNT_HW_INSTRUCTIONS":0,"PERF_COUNT_HW_BRANCH_MISSES":0,"PERF_COUNT_HW_CACHE_REFERENCES":0,"PERF_COUNT_HW_CPU_CYCLES":0}}
{"runtime":2579,"energy":{"pkg":193.3375244140625,"pp0":0,"dram":38.05462646484375},"perf_counters":{"PERF_COUNT_HW_REF_CPU_CYCLES":0,"PERF_COUNT_HW_BRANCH_INSTRUCTIONS":0,"PERF_COUNT_HW_CACHE_MISSES":0,"PERF_COUNT_HW_INSTRUCTIONS":0,"PERF_COUNT_HW_BRANCH_MISSES":0,"PERF_COUNT_HW_CACHE_REFERENCES":0,"PERF_COUNT_HW_CPU_CYCLES":0}}
{"runtime":2650,"energy":{"pkg":196.12725830078125,"pp0":0,"dram":39.01593017578125},"perf_counters":{"PERF_COUNT_HW_REF_CPU_CYCLES":0,"PERF_COUNT_HW_BRANCH_INSTRUCTIONS":0,"PERF_COUNT_HW_CACHE_MISSES":0,"PERF_COUNT_HW_INSTRUCTIONS":0,"PERF_COUNT_HW_BRANCH_MISSES":0,"PERF_COUNT_HW_CACHE_REFERENCES":0,"PERF_COUNT_HW_CPU_CYCLES":0}}
{"runtime":2615,"energy":{"pkg":194.038330078125,"pp0":0,"dram":38.658447265625},"perf_counters":{"PERF_COUNT_HW_REF_CPU_CYCLES":0,"PERF_COUNT_HW_BRANCH_INSTRUCTIONS":0,"PERF_COUNT_HW_CACHE_MISSES":0,"PERF_COUNT_HW_INSTRUCTIONS":0,"PERF_COUNT_HW_BRANCH_MISSES":0,"PERF_COUNT_HW_CACHE_REFERENCES":0,"PERF_COUNT_HW_CPU_CYCLES":0}}
{"runtime":2667,"energy":{"pkg":197.263916015625,"pp0":0,"dram":39.20465087890625},"perf_counters":{"PERF_COUNT_HW_REF_CPU_CYCLES":0,"PERF_COUNT_HW_BRANCH_INSTRUCTIONS":0,"PERF_COUNT_HW_CACHE_MISSES":0,"PERF_COUNT_HW_INSTRUCTIONS":0,"PERF_COUNT_HW_BRANCH_MISSES":0,"PERF_COUNT_HW_CACHE_REFERENCES":0,"PERF_COUNT_HW_CPU_CYCLES":0}}
{"runtime":2637,"energy":{"pkg":195.112548828125,"pp0":0,"dram":39.0421142578125},"perf_counters":{"PERF_COUNT_HW_REF_CPU_CYCLES":0,"PERF_COUNT_HW_BRANCH_INSTRUCTIONS":0,"PERF_COUNT_HW_CACHE_MISSES":0,"PERF_COUNT_HW_INSTRUCTIONS":0,"PERF_COUNT_HW_BRANCH_MISSES":0,"PERF_COUNT_HW_CACHE_REFERENCES":0,"PERF_COUNT_HW_CPU_CYCLES":0}}
{"runtime":2613,"energy":{"pkg":194.39306640625,"pp0":0,"dram":38.46490478515625},"perf_counters":{"PERF_COUNT_HW_REF_CPU_CYCLES":0,"PERF_COUNT_HW_BRANCH_INSTRUCTIONS":0,"PERF_COUNT_HW_CACHE_MISSES":0,"PERF_COUNT_HW_INSTRUCTIONS":0,"PERF_COUNT_HW_BRANCH_MISSES":0,"PERF_COUNT_HW_CACHE_REFERENCES":0,"PERF_COUNT_HW_CPU_CYCLES":0}}
{"runtime":2604,"energy":{"pkg":193.12823486328125,"pp0":0,"dram":38.517578125},"perf_counters":{"PERF_COUNT_HW_REF_CPU_CYCLES":0,"PERF_COUNT_HW_BRANCH_INSTRUCTIONS":0,"PERF_COUNT_HW_CACHE_MISSES":0,"PERF_COUNT_HW_INSTRUCTIONS":0,"PERF_COUNT_HW_BRANCH_MISSES":0,"PERF_COUNT_HW_CACHE_REFERENCES":0,"PERF_COUNT_HW_CPU_CYCLES":0}}
{"runtime":2666,"energy":{"pkg":196.15863037109375,"pp0":0,"dram":39.2540283203125},"perf_counters":{"PERF_COUNT_HW_REF_CPU_CYCLES":0,"PERF_COUNT_HW_BRANCH_INSTRUCTIONS":0,"PERF_COUNT_HW_CACHE_MISSES":0,"PERF_COUNT_HW_INSTRUCTIONS":0,"PERF_COUNT_HW_BRANCH_MISSES":0,"PERF_COUNT_HW_CACHE_REFERENCES":0,"PERF_COUNT_HW_CPU_CYCLES":0}}
{"runtime":2529,"energy":{"pkg":191.51776123046875,"pp0":0,"dram":37.74066162109375},"perf_counters":{"PERF_COUNT_HW_REF_CPU_CYCLES":0,"PERF_COUNT_HW_BRANCH_INSTRUCTIONS":0,"PERF_COUNT_HW_CACHE_MISSES":0,"PERF_COUNT_HW_INSTRUCTIONS":0,"PERF_COUNT_HW_BRANCH_MISSES":0,"PERF_COUNT_HW_CACHE_REFERENCES":0,"PERF_COUNT_HW_CPU_CYCLES":0}}
{"runtime":2595,"energy":{"pkg":192.66705322265625,"pp0":0,"dram":38.8184814453125},"perf_counters":{"PERF_COUNT_HW_REF_CPU_CYCLES":0,"PERF_COUNT_HW_BRANCH_INSTRUCTIONS":0,"PERF_COUNT_HW_CACHE_MISSES":0,"PERF_COUNT_HW_INSTRUCTIONS":0,"PERF_COUNT_HW_BRANCH_MISSES":0,"PERF_COUNT_HW_CACHE_REFERENCES":0,"PERF_COUNT_HW_CPU_CYCLES":0}}
{"runtime":2772,"energy":{"pkg":199.8909912109375,"pp0":0,"dram":40.225341796875},"perf_counters":{"PERF_COUNT_HW_REF_CPU_CYCLES":0,"PERF_COUNT_HW_BRANCH_INSTRUCTIONS":0,"PERF_COUNT_HW_CACHE_MISSES":0,"PERF_COUNT_HW_INSTRUCTIONS":0,"PERF_COUNT_HW_BRANCH_MISSES":0,"PERF_COUNT_HW_CACHE_REFERENCES":0,"PERF_COUNT_HW_CPU_CYCLES":0}}
{"runtime":2609,"energy":{"pkg":193.48565673828125,"pp0":0,"dram":38.3299560546875},"perf_counters":{"PERF_COUNT_HW_REF_CPU_CYCLES":0,"PERF_COUNT_HW_BRANCH_INSTRUCTIONS":0,"PERF_COUNT_HW_CACHE_MISSES":0,"PERF_COUNT_HW_INSTRUCTIONS":0,"PERF_COUNT_HW_BRANCH_MISSES":0,"PERF_COUNT_HW_CACHE_REFERENCES":0,"PERF_COUNT_HW_CPU_CYCLES":0}}
{"runtime":2541,"energy":{"pkg":190.8626708984375,"pp0":0,"dram":37.806640625},"perf_counters":{"PERF_COUNT_HW_REF_CPU_CYCLES":0,"PERF_COUNT_HW_BRANCH_INSTRUCTIONS":0,"PERF_COUNT_HW_CACHE_MISSES":0,"PERF_COUNT_HW_INSTRUCTIONS":0,"PERF_COUNT_HW_BRANCH_MISSES":0,"PERF_COUNT_HW_CACHE_REFERENCES":0,"PERF_COUNT_HW_CPU_CYCLES":0}}
