{"runtime":1638,"energy":{"pkg":48.84033203125,"pp0":0,"dram":12.275634765625},"rusage":{"ru_utime":{"tv_sec":1,"tv_usec":634294},"ru_stime":{"tv_sec":0,"tv_usec":36289},"ru_maxrss":18860,"ru_ixrss":0,"ru_idrss":0,"ru_isrss":0,"ru_minflt":778,"ru_majflt":0,"ru_nswap":0,"ru_inblock":0,"ru_oublock":0,"ru_msgsnd":0,"ru_msgrcv":0,"ru_nsignals":0,"ru_nvcsw":5625,"ru_nivcsw":120}}
{"runtime":1651,"energy":{"pkg":46.0225830078125,"pp0":0,"dram":14.404296875},"rusage":{"ru_utime":{"tv_sec":1,"tv_usec":655877},"ru_stime":{"tv_sec":0,"tv_usec":28457},"ru_maxrss":18804,"ru_ixrss":0,"ru_idrss":0,"ru_isrss":0,"ru_minflt":758,"ru_majflt":0,"ru_nswap":0,"ru_inblock":0,"ru_oublock":0,"ru_msgsnd":0,"ru_msgrcv":0,"ru_nsignals":0,"ru_nvcsw":5389,"ru_nivcsw":125}}
{"runtime":1601,"energy":{"pkg":48.051513671875,"pp0":0,"dram":12.35321044921875},"rusage":{"ru_utime":{"tv_sec":1,"tv_usec":600019},"ru_stime":{"tv_sec":0,"tv_usec":32377},"ru_maxrss":19048,"ru_ixrss":0,"ru_idrss":0,"ru_isrss":0,"ru_minflt":794,"ru_majflt":0,"ru_nswap":0,"ru_inblock":0,"ru_oublock":0,"ru_msgsnd":0,"ru_msgrcv":0,"ru_nsignals":0,"ru_nvcsw":5492,"ru_nivcsw":129}}
{"runtime":1638,"energy":{"pkg":49.01812744140625,"pp0":0,"dram":12.32818603515625},"rusage":{"ru_utime":{"tv_sec":1,"tv_usec":649198},"ru_stime":{"tv_sec":0,"tv_usec":20344},"ru_maxrss":19032,"ru_ixrss":0,"ru_idrss":0,"ru_isrss":0,"ru_minflt":813,"ru_majflt":0,"ru_nswap":0,"ru_inblock":0,"ru_oublock":0,"ru_msgsnd":0,"ru_msgrcv":0,"ru_nsignals":0,"ru_nvcsw":5449,"ru_nivcsw":122}}
{"runtime":1599,"energy":{"pkg":48.15380859375,"pp0":0,"dram":12.080810546875},"rusage":{"ru_utime":{"tv_sec":1,"tv_usec":575449},"ru_stime":{"tv_sec":0,"tv_usec":56364},"ru_maxrss":18960,"ru_ixrss":0,"ru_idrss":0,"ru_isrss":0,"ru_minflt":788,"ru_majflt":0,"ru_nswap":0,"ru_inblock":0,"ru_oublock":0,"ru_msgsnd":0,"ru_msgrcv":0,"ru_nsignals":0,"ru_nvcsw":5621,"ru_nivcsw":122}}
{"runtime":1588,"energy":{"pkg":45.3065185546875,"pp0":0,"dram":13.9757080078125},"rusage":{"ru_utime":{"tv_sec":1,"tv_usec":576234},"ru_stime":{"tv_sec":0,"tv_usec":44307},"ru_maxrss":18992,"ru_ixrss":0,"ru_idrss":0,"ru_isrss":0,"ru_minflt":816,"ru_majflt":0,"ru_nswap":0,"ru_inblock":0,"ru_oublock":0,"ru_msgsnd":0,"ru_msgrcv":0,"ru_nsignals":0,"ru_nvcsw":5324,"ru_nivcsw":125}}
{"runtime":1600,"energy":{"pkg":47.74591064453125,"pp0":0,"dram":12.04766845703125},"rusage":{"ru_utime":{"tv_sec":1,"tv_usec":595535},"ru_stime":{"tv_sec":0,"tv_usec":36415},"ru_maxrss":18928,"ru_ixrss":0,"ru_idrss":0,"ru_isrss":0,"ru_minflt":790,"ru_majflt":0,"ru_nswap":0,"ru_inblock":0,"ru_oublock":0,"ru_msgsnd":0,"ru_msgrcv":0,"ru_nsignals":0,"ru_nvcsw":5565,"ru_nivcsw":121}}
{"runtime":1645,"energy":{"pkg":46.26025390625,"pp0":0,"dram":14.203125},"rusage":{"ru_utime":{"tv_sec":1,"tv_usec":653315},"ru_stime":{"tv_sec":0,"tv_usec":24473},"ru_maxrss":19028,"ru_ixrss":0,"ru_idrss":0,"ru_isrss":0,"ru_minflt":815,"ru_majflt":0,"ru_nswap":0,"ru_inblock":0,"ru_oublock":0,"ru_msgsnd":0,"ru_msgrcv":0,"ru_nsignals":0,"ru_nvcsw":5276,"ru_nivcsw":128}}
{"runtime":1611,"energy":{"pkg":48.510498046875,"pp0":0,"dram":12.1474609375},"rusage":{"ru_utime":{"tv_sec":1,"tv_usec":612552},"ru_stime":{"tv_sec":0,"tv_usec":32550},"ru_maxrss":19008,"ru_ixrss":0,"ru_idrss":0,"ru_isrss":0,"ru_minflt":788,"ru_majflt":0,"ru_nswap":0,"ru_inblock":0,"ru_oublock":0,"ru_msgsnd":0,"ru_msgrcv":0,"ru_nsignals":0,"ru_nvcsw":5681,"ru_nivcsw":119}}
{"runtime":1593,"energy":{"pkg":48.289794921875,"pp0":0,"dram":11.96881103515625},"rusage":{"ru_utime":{"tv_sec":1,"tv_usec":600478},"ru_stime":{"tv_sec":0,"tv_usec":24415},"ru_maxrss":18984,"ru_ixrss":0,"ru_idrss":0,"ru_isrss":0,"ru_minflt":814,"ru_majflt":0,"ru_nswap":0,"ru_inblock":0,"ru_oublock":0,"ru_msgsnd":0,"ru_msgrcv":0,"ru_nsignals":0,"ru_nvcsw":5469,"ru_nivcsw":116}}
{"runtime":1597,"energy":{"pkg":48.64892578125,"pp0":0,"dram":12.2640380859375},"rusage":{"ru_utime":{"tv_sec":1,"tv_usec":598895},"ru_stime":{"tv_sec":0,"tv_usec":28458},"ru_maxrss":19104,"ru_ixrss":0,"ru_idrss":0,"ru_isrss":0,"ru_minflt":832,"ru_majflt":0,"ru_nswap":0,"ru_inblock":0,"ru_oublock":0,"ru_msgsnd":0,"ru_msgrcv":0,"ru_nsignals":0,"ru_nvcsw":5159,"ru_nivcsw":125}}
{"runtime":1623,"energy":{"pkg":49.38421630859375,"pp0":0,"dram":12.2606201171875},"rusage":{"ru_utime":{"tv_sec":1,"tv_usec":611114},"ru_stime":{"tv_sec":0,"tv_usec":44270},"ru_maxrss":18976,"ru_ixrss":0,"ru_idrss":0,"ru_isrss":0,"ru_minflt":814,"ru_majflt":0,"ru_nswap":0,"ru_inblock":0,"ru_oublock":0,"ru_msgsnd":0,"ru_msgrcv":0,"ru_nsignals":0,"ru_nvcsw":5685,"ru_nivcsw":126}}
{"runtime":1578,"energy":{"pkg":45.21990966796875,"pp0":0,"dram":13.8115234375},"rusage":{"ru_utime":{"tv_sec":1,"tv_usec":581081},"ru_stime":{"tv_sec":0,"tv_usec":28355},"ru_maxrss":18968,"ru_ixrss":0,"ru_idrss":0,"ru_isrss":0,"ru_minflt":777,"ru_majflt":0,"ru_nswap":0,"ru_inblock":0,"ru_oublock":0,"ru_msgsnd":0,"ru_msgrcv":0,"ru_nsignals":0,"ru_nvcsw":5214,"ru_nivcsw":120}}
{"runtime":1635,"energy":{"pkg":45.823486328125,"pp0":0,"dram":14.51507568359375},"rusage":{"ru_utime":{"tv_sec":1,"tv_usec":642748},"ru_stime":{"tv_sec":0,"tv_usec":24498},"ru_maxrss":19048,"ru_ixrss":0,"ru_idrss":0,"ru_isrss":0,"ru_minflt":810,"ru_majflt":0,"ru_nswap":0,"ru_inblock":0,"ru_oublock":0,"ru_msgsnd":0,"ru_msgrcv":0,"ru_nsignals":0,"ru_nvcsw":5629,"ru_nivcsw":124}}
{"runtime":1553,"energy":{"pkg":46.83837890625,"pp0":0,"dram":12.1202392578125},"rusage":{"ru_utime":{"tv_sec":1,"tv_usec":534174},"ru_stime":{"tv_sec":0,"tv_usec":49784},"ru_maxrss":18848,"ru_ixrss":0,"ru_idrss":0,"ru_isrss":0,"ru_minflt":760,"ru_majflt":0,"ru_nswap":0,"ru_inblock":0,"ru_oublock":0,"ru_msgsnd":0,"ru_msgrcv":0,"ru_nsignals":0,"ru_nvcsw":5268,"ru_nivcsw":117}}
{"runtime":1537,"energy":{"pkg":47.82806396484375,"pp0":0,"dram":11.75274658203125},"rusage":{"ru_utime":{"tv_sec":1,"tv_usec":523204},"ru_stime":{"tv_sec":0,"tv_usec":44169},"ru_maxrss":18964,"ru_ixrss":0,"ru_idrss":0,"ru_isrss":0,"ru_minflt":789,"ru_majflt":0,"ru_nswap":0,"ru_inblock":0,"ru_oublock":0,"ru_msgsnd":0,"ru_msgrcv":0,"ru_nsignals":0,"ru_nvcsw":5387,"ru_nivcsw":114}}
{"runtime":1635,"energy":{"pkg":49.21795654296875,"pp0":0,"dram":12.3687744140625},"rusage":{"ru_utime":{"tv_sec":1,"tv_usec":624863},"ru_stime":{"tv_sec":0,"tv_usec":43879},"ru_maxrss":18920,"ru_ixrss":0,"ru_idrss":0,"ru_isrss":0,"ru_minflt":779,"ru_majflt":0,"ru_nswap":0,"ru_inblock":0,"ru_oublock":0,"ru_msgsnd":0,"ru_msgrcv":0,"ru_nsignals":0,"ru_nvcsw":5978,"ru_nivcsw":126}}
{"runtime":1616,"energy":{"pkg":48.78155517578125,"pp0":0,"dram":12.16015625},"rusage":{"ru_utime":{"tv_sec":1,"tv_usec":621866},"ru_stime":{"tv_sec":0,"tv_usec":24187},"ru_maxrss":18832,"ru_ixrss":0,"ru_idrss":0,"ru_isrss":0,"ru_minflt":770,"ru_majflt":0,"ru_nswap":0,"ru_inblock":0,"ru_oublock":0,"ru_msgsnd":0,"ru_msgrcv":0,"ru_nsignals":0,"ru_nvcsw":5098,"ru_nivcsw":125}}
{"runtime":1603,"energy":{"pkg":48.37725830078125,"pp0":0,"dram":12.02197265625},"rusage":{"ru_utime":{"tv_sec":1,"tv_usec":602100},"ru_stime":{"tv_sec":0,"tv_usec":32340},"ru_maxrss":18980,"ru_ixrss":0,"ru_idrss":0,"ru_isrss":0,"ru_minflt":778,"ru_majflt":0,"ru_nswap":0,"ru_inblock":0,"ru_oublock":0,"ru_msgsnd":0,"ru_msgrcv":0,"ru_nsignals":0,"ru_nvcsw":5209,"ru_nivcsw":122}}
{"runtime":1621,"energy":{"pkg":48.49517822265625,"pp0":0,"dram":12.0875244140625},"rusage":{"ru_utime":{"tv_sec":1,"tv_usec":621986},"ru_stime":{"tv_sec":0,"tv_usec":33609},"ru_maxrss":18924,"ru_ixrss":0,"ru_idrss":0,"ru_isrss":0,"ru_minflt":816,"ru_majflt":0,"ru_nswap":0,"ru_inblock":0,"ru_oublock":0,"ru_msgsnd":0,"ru_msgrcv":0,"ru_nsignals":0,"ru_nvcsw":5962,"ru_nivcsw":119}}
{"runtime":1626,"energy":{"pkg":49.21795654296875,"pp0":0,"dram":12.20562744140625},"rusage":{"ru_utime":{"tv_sec":1,"tv_usec":609606},"ru_stime":{"tv_sec":0,"tv_usec":48010},"ru_maxrss":19032,"ru_ixrss":0,"ru_idrss":0,"ru_isrss":0,"ru_minflt":814,"ru_majflt":0,"ru_nswap":0,"ru_inblock":0,"ru_oublock":0,"ru_msgsnd":0,"ru_msgrcv":0,"ru_nsignals":0,"ru_nvcsw":5629,"ru_nivcsw":121}}
