{"runtime":636,"energy":{"pkg":45.51141357421875,"pp0":0,"dram":12.9490966796875},"rusage":{"ru_utime":{"tv_sec":11,"tv_usec":27227},"ru_stime":{"tv_sec":0,"tv_usec":827665},"ru_maxrss":767412,"ru_ixrss":0,"ru_idrss":0,"ru_isrss":0,"ru_minflt":224588,"ru_majflt":0,"ru_nswap":0,"ru_inblock":0,"ru_oublock":0,"ru_msgsnd":0,"ru_msgrcv":0,"ru_nsignals":0,"ru_nvcsw":1443,"ru_nivcsw":1255}}
{"runtime":629,"energy":{"pkg":44.77001953125,"pp0":0,"dram":12.08062744140625},"rusage":{"ru_utime":{"tv_sec":11,"tv_usec":423453},"ru_stime":{"tv_sec":0,"tv_usec":806697},"ru_maxrss":778628,"ru_ixrss":0,"ru_idrss":0,"ru_isrss":0,"ru_minflt":227261,"ru_majflt":0,"ru_nswap":0,"ru_inblock":0,"ru_oublock":0,"ru_msgsnd":0,"ru_msgrcv":0,"ru_nsignals":0,"ru_nvcsw":2196,"ru_nivcsw":1469}}
{"runtime":643,"energy":{"pkg":44.31829833984375,"pp0":0,"dram":11.6419677734375},"rusage":{"ru_utime":{"tv_sec":9,"tv_usec":989633},"ru_stime":{"tv_sec":0,"tv_usec":757793},"ru_maxrss":766300,"ru_ixrss":0,"ru_idrss":0,"ru_isrss":0,"ru_minflt":224430,"ru_majflt":0,"ru_nswap":0,"ru_inblock":0,"ru_oublock":0,"ru_msgsnd":0,"ru_msgrcv":0,"ru_nsignals":0,"ru_nvcsw":2209,"ru_nivcsw":1536}}
{"runtime":575,"energy":{"pkg":41.3079833984375,"pp0":0,"dram":11.751220703125},"rusage":{"ru_utime":{"tv_sec":9,"tv_usec":306970},"ru_stime":{"tv_sec":0,"tv_usec":803263},"ru_maxrss":739224,"ru_ixrss":0,"ru_idrss":0,"ru_isrss":0,"ru_minflt":217779,"ru_majflt":0,"ru_nswap":0,"ru_inblock":0,"ru_oublock":0,"ru_msgsnd":0,"ru_msgrcv":0,"ru_nsignals":0,"ru_nvcsw":2109,"ru_nivcsw":1126}}
{"runtime":633,"energy":{"pkg":44.40838623046875,"pp0":0,"dram":12.36822509765625},"rusage":{"ru_utime":{"tv_sec":10,"tv_usec":242239},"ru_stime":{"tv_sec":0,"tv_usec":909954},"ru_maxrss":829548,"ru_ixrss":0,"ru_idrss":0,"ru_isrss":0,"ru_minflt":240077,"ru_majflt":0,"ru_nswap":0,"ru_inblock":0,"ru_oublock":0,"ru_msgsnd":0,"ru_msgrcv":0,"ru_nsignals":0,"ru_nvcsw":2542,"ru_nivcsw":1289}}
{"runtime":652,"energy":{"pkg":45.430908203125,"pp0":0,"dram":11.63922119140625},"rusage":{"ru_utime":{"tv_sec":10,"tv_usec":38411},"ru_stime":{"tv_sec":1,"tv_usec":27898},"ru_maxrss":846396,"ru_ixrss":0,"ru_idrss":0,"ru_isrss":0,"ru_minflt":244203,"ru_majflt":0,"ru_nswap":0,"ru_inblock":0,"ru_oublock":0,"ru_msgsnd":0,"ru_msgrcv":0,"ru_nsignals":0,"ru_nvcsw":2582,"ru_nivcsw":1264}}
{"runtime":621,"energy":{"pkg":44.09283447265625,"pp0":0,"dram":11.38934326171875},"rusage":{"ru_utime":{"tv_sec":10,"tv_usec":106752},"ru_stime":{"tv_sec":1,"tv_usec":167724},"ru_maxrss":880072,"ru_ixrss":0,"ru_idrss":0,"ru_isrss":0,"ru_minflt":252726,"ru_majflt":0,"ru_nswap":0,"ru_inblock":0,"ru_oublock":0,"ru_msgsnd":0,"ru_msgrcv":0,"ru_nsignals":0,"ru_nvcsw":2613,"ru_nivcsw":1237}}
{"runtime":555,"energy":{"pkg":39.5966796875,"pp0":0,"dram":11.28125},"rusage":{"ru_utime":{"tv_sec":9,"tv_usec":396982},"ru_stime":{"tv_sec":0,"tv_usec":582743},"ru_maxrss":572216,"ru_ixrss":0,"ru_idrss":0,"ru_isrss":0,"ru_minflt":176229,"ru_majflt":0,"ru_nswap":0,"ru_inblock":0,"ru_oublock":0,"ru_msgsnd":0,"ru_msgrcv":0,"ru_nsignals":0,"ru_nvcsw":1161,"ru_nivcsw":1081}}
{"runtime":634,"energy":{"pkg":43.9453125,"pp0":0,"dram":11.7955322265625},"rusage":{"ru_utime":{"tv_sec":9,"tv_usec":934566},"ru_stime":{"tv_sec":0,"tv_usec":876592},"ru_maxrss":782988,"ru_ixrss":0,"ru_idrss":0,"ru_isrss":0,"ru_minflt":228479,"ru_majflt":0,"ru_nswap":0,"ru_inblock":0,"ru_oublock":0,"ru_msgsnd":0,"ru_msgrcv":0,"ru_nsignals":0,"ru_nvcsw":1998,"ru_nivcsw":1458}}
{"runtime":667,"energy":{"pkg":48.2249755859375,"pp0":0,"dram":12.71197509765625},"rusage":{"ru_utime":{"tv_sec":11,"tv_usec":94525},"ru_stime":{"tv_sec":1,"tv_usec":349765},"ru_maxrss":899548,"ru_ixrss":0,"ru_idrss":0,"ru_isrss":0,"ru_minflt":257491,"ru_majflt":0,"ru_nswap":0,"ru_inblock":0,"ru_oublock":0,"ru_msgsnd":0,"ru_msgrcv":0,"ru_nsignals":0,"ru_nvcsw":2429,"ru_nivcsw":1465}}
{"runtime":602,"energy":{"pkg":42.18841552734375,"pp0":0,"dram":11.6641845703125},"rusage":{"ru_utime":{"tv_sec":9,"tv_usec":305938},"ru_stime":{"tv_sec":0,"tv_usec":758993},"ru_maxrss":800616,"ru_ixrss":0,"ru_idrss":0,"ru_isrss":0,"ru_minflt":232778,"ru_majflt":0,"ru_nswap":0,"ru_inblock":0,"ru_oublock":0,"ru_msgsnd":0,"ru_msgrcv":0,"ru_nsignals":0,"ru_nvcsw":2240,"ru_nivcsw":1220}}
{"runtime":660,"energy":{"pkg":45.42816162109375,"pp0":0,"dram":12.29254150390625},"rusage":{"ru_utime":{"tv_sec":10,"tv_usec":217575},"ru_stime":{"tv_sec":0,"tv_usec":903428},"ru_maxrss":825948,"ru_ixrss":0,"ru_idrss":0,"ru_isrss":0,"ru_minflt":239010,"ru_majflt":0,"ru_nswap":0,"ru_inblock":0,"ru_oublock":0,"ru_msgsnd":0,"ru_msgrcv":0,"ru_nsignals":0,"ru_nvcsw":1799,"ru_nivcsw":1340}}
{"runtime":610,"energy":{"pkg":43.732666015625,"pp0":0,"dram":12.3150634765625},"rusage":{"ru_utime":{"tv_sec":10,"tv_usec":689895},"ru_stime":{"tv_sec":0,"tv_usec":831783},"ru_maxrss":753364,"ru_ixrss":0,"ru_idrss":0,"ru_isrss":0,"ru_minflt":220961,"ru_majflt":0,"ru_nswap":0,"ru_inblock":0,"ru_oublock":0,"ru_msgsnd":0,"ru_msgrcv":0,"ru_nsignals":0,"ru_nvcsw":1768,"ru_nivcsw":1760}}
{"runtime":637,"energy":{"pkg":45.07330322265625,"pp0":0,"dram":11.84930419921875},"rusage":{"ru_utime":{"tv_sec":10,"tv_usec":89549},"ru_stime":{"tv_sec":1,"tv_usec":188278},"ru_maxrss":875828,"ru_ixrss":0,"ru_idrss":0,"ru_isrss":0,"ru_minflt":251622,"ru_majflt":0,"ru_nswap":0,"ru_inblock":0,"ru_oublock":0,"ru_msgsnd":0,"ru_msgrcv":0,"ru_nsignals":0,"ru_nvcsw":2251,"ru_nivcsw":1712}}
{"runtime":618,"energy":{"pkg":44.30926513671875,"pp0":0,"dram":11.83154296875},"rusage":{"ru_utime":{"tv_sec":9,"tv_usec":688859},"ru_stime":{"tv_sec":1,"tv_usec":234066},"ru_maxrss":942564,"ru_ixrss":0,"ru_idrss":0,"ru_isrss":0,"ru_minflt":268163,"ru_majflt":0,"ru_nswap":0,"ru_inblock":0,"ru_oublock":0,"ru_msgsnd":0,"ru_msgrcv":0,"ru_nsignals":0,"ru_nvcsw":2238,"ru_nivcsw":1188}}
{"runtime":666,"energy":{"pkg":47.255859375,"pp0":0,"dram":12.53692626953125},"rusage":{"ru_utime":{"tv_sec":10,"tv_usec":935529},"ru_stime":{"tv_sec":1,"tv_usec":368281},"ru_maxrss":950312,"ru_ixrss":0,"ru_idrss":0,"ru_isrss":0,"ru_minflt":270119,"ru_majflt":0,"ru_nswap":0,"ru_inblock":0,"ru_oublock":0,"ru_msgsnd":0,"ru_msgrcv":0,"ru_nsignals":0,"ru_nvcsw":2301,"ru_nivcsw":1691}}
{"runtime":648,"energy":{"pkg":45.16998291015625,"pp0":0,"dram":11.75201416015625},"rusage":{"ru_utime":{"tv_sec":9,"tv_usec":701664},"ru_stime":{"tv_sec":1,"tv_usec":257455},"ru_maxrss":879480,"ru_ixrss":0,"ru_idrss":0,"ru_isrss":0,"ru_minflt":252536,"ru_majflt":0,"ru_nswap":0,"ru_inblock":0,"ru_oublock":0,"ru_msgsnd":0,"ru_msgrcv":0,"ru_nsignals":0,"ru_nvcsw":3002,"ru_nivcsw":1374}}
{"runtime":614,"energy":{"pkg":44.0986328125,"pp0":0,"dram":11.7872314453125},"rusage":{"ru_utime":{"tv_sec":9,"tv_usec":477031},"ru_stime":{"tv_sec":1,"tv_usec":18938},"ru_maxrss":878152,"ru_ixrss":0,"ru_idrss":0,"ru_isrss":0,"ru_minflt":252148,"ru_majflt":0,"ru_nswap":0,"ru_inblock":0,"ru_oublock":0,"ru_msgsnd":0,"ru_msgrcv":0,"ru_nsignals":0,"ru_nvcsw":2365,"ru_nivcsw":1341}}
{"runtime":615,"energy":{"pkg":43.58770751953125,"pp0":0,"dram":11.58123779296875},"rusage":{"ru_utime":{"tv_sec":10,"tv_usec":565282},"ru_stime":{"tv_sec":0,"tv_usec":855770},"ru_maxrss":805780,"ru_ixrss":0,"ru_idrss":0,"ru_isrss":0,"ru_minflt":234088,"ru_majflt":0,"ru_nswap":0,"ru_inblock":0,"ru_oublock":0,"ru_msgsnd":0,"ru_msgrcv":0,"ru_nsignals":0,"ru_nvcsw":2477,"ru_nivcsw":1314}}
{"runtime":598,"energy":{"pkg":41.864501953125,"pp0":0,"dram":11.12286376953125},"rusage":{"ru_utime":{"tv_sec":9,"tv_usec":131902},"ru_stime":{"tv_sec":0,"tv_usec":742590},"ru_maxrss":842336,"ru_ixrss":0,"ru_idrss":0,"ru_isrss":0,"ru_minflt":243232,"ru_majflt":0,"ru_nswap":0,"ru_inblock":0,"ru_oublock":0,"ru_msgsnd":0,"ru_msgrcv":0,"ru_nsignals":0,"ru_nvcsw":1860,"ru_nivcsw":1140}}
{"runtime":642,"energy":{"pkg":46.1136474609375,"pp0":0,"dram":12.24261474609375},"rusage":{"ru_utime":{"tv_sec":10,"tv_usec":663575},"ru_stime":{"tv_sec":0,"tv_usec":965275},"ru_maxrss":848352,"ru_ixrss":0,"ru_idrss":0,"ru_isrss":0,"ru_minflt":244769,"ru_majflt":0,"ru_nswap":0,"ru_inblock":0,"ru_oublock":0,"ru_msgsnd":0,"ru_msgrcv":0,"ru_nsignals":0,"ru_nvcsw":2046,"ru_nivcsw":1643}}
