{"runtime":8136,"energy":{"pkg":421.29595947265625,"pp0":0,"dram":153.9423828125},"rusage":{"ru_utime":{"tv_sec":42,"tv_usec":97761},"ru_stime":{"tv_sec":6,"tv_usec":464794},"ru_maxrss":4809660,"ru_ixrss":0,"ru_idrss":0,"ru_isrss":0,"ru_minflt":1269926,"ru_majflt":8,"ru_nswap":0,"ru_inblock":0,"ru_oublock":64,"ru_msgsnd":0,"ru_msgrcv":0,"ru_nsignals":0,"ru_nvcsw":57241,"ru_nivcsw":3845}}
{"runtime":7839,"energy":{"pkg":407.68548583984375,"pp0":0,"dram":148.81207275390625},"rusage":{"ru_utime":{"tv_sec":40,"tv_usec":732790},"ru_stime":{"tv_sec":5,"tv_usec":928096},"ru_maxrss":4807380,"ru_ixrss":0,"ru_idrss":0,"ru_isrss":0,"ru_minflt":1269226,"ru_majflt":8,"ru_nswap":0,"ru_inblock":0,"ru_oublock":64,"ru_msgsnd":0,"ru_msgrcv":0,"ru_nsignals":0,"ru_nvcsw":54707,"ru_nivcsw":3822}}
{"runtime":8879,"energy":{"pkg":444.16119384765625,"pp0":0,"dram":165.58349609375},"rusage":{"ru_utime":{"tv_sec":46,"tv_usec":888098},"ru_stime":{"tv_sec":6,"tv_usec":731073},"ru_maxrss":4773940,"ru_ixrss":0,"ru_idrss":0,"ru_isrss":0,"ru_minflt":1272381,"ru_majflt":8,"ru_nswap":0,"ru_inblock":0,"ru_oublock":64,"ru_msgsnd":0,"ru_msgrcv":0,"ru_nsignals":0,"ru_nvcsw":59806,"ru_nivcsw":4604}}
{"runtime":8468,"energy":{"pkg":430.060546875,"pp0":0,"dram":153.4462890625},"rusage":{"ru_utime":{"tv_sec":44,"tv_usec":622533},"ru_stime":{"tv_sec":6,"tv_usec":647224},"ru_maxrss":4758784,"ru_ixrss":0,"ru_idrss":0,"ru_isrss":0,"ru_minflt":1257276,"ru_majflt":8,"ru_nswap":0,"ru_inblock":0,"ru_oublock":64,"ru_msgsnd":0,"ru_msgrcv":0,"ru_nsignals":0,"ru_nvcsw":63740,"ru_nivcsw":4376}}
{"runtime":8596,"energy":{"pkg":422.8544921875,"pp0":0,"dram":162.6524658203125},"rusage":{"ru_utime":{"tv_sec":44,"tv_usec":265264},"ru_stime":{"tv_sec":6,"tv_usec":674134},"ru_maxrss":4794688,"ru_ixrss":0,"ru_idrss":0,"ru_isrss":0,"ru_minflt":1273812,"ru_majflt":8,"ru_nswap":0,"ru_inblock":0,"ru_oublock":64,"ru_msgsnd":0,"ru_msgrcv":0,"ru_nsignals":0,"ru_nvcsw":63062,"ru_nivcsw":4147}}
{"runtime":8495,"energy":{"pkg":437.85260009765625,"pp0":0,"dram":160.531494140625},"rusage":{"ru_utime":{"tv_sec":42,"tv_usec":882288},"ru_stime":{"tv_sec":6,"tv_usec":571410},"ru_maxrss":4805136,"ru_ixrss":0,"ru_idrss":0,"ru_isrss":0,"ru_minflt":1268697,"ru_majflt":8,"ru_nswap":0,"ru_inblock":0,"ru_oublock":64,"ru_msgsnd":0,"ru_msgrcv":0,"ru_nsignals":0,"ru_nvcsw":48895,"ru_nivcsw":4369}}
{"runtime":9284,"energy":{"pkg":455.773681640625,"pp0":0,"dram":161.8529052734375},"rusage":{"ru_utime":{"tv_sec":45,"tv_usec":538746},"ru_stime":{"tv_sec":6,"tv_usec":939841},"ru_maxrss":4757180,"ru_ixrss":0,"ru_idrss":0,"ru_isrss":0,"ru_minflt":1256721,"ru_majflt":8,"ru_nswap":0,"ru_inblock":0,"ru_oublock":64,"ru_msgsnd":0,"ru_msgrcv":0,"ru_nsignals":0,"ru_nvcsw":59104,"ru_nivcsw":4514}}
