{"runtime":7265,"energy":{"pkg":134.6119384765625,"pp0":0,"dram":34.9825439453125},"rusage":{"ru_utime":{"tv_sec":6,"tv_usec":868890},"ru_stime":{"tv_sec":0,"tv_usec":319880},"ru_maxrss":134244,"ru_ixrss":0,"ru_idrss":0,"ru_isrss":0,"ru_minflt":60667,"ru_majflt":0,"ru_nswap":0,"ru_inblock":0,"ru_oublock":0,"ru_msgsnd":0,"ru_msgrcv":0,"ru_nsignals":0,"ru_nvcsw":742,"ru_nivcsw":1182}}
{"runtime":7038,"energy":{"pkg":130.95013427734375,"pp0":0,"dram":33.45416259765625},"rusage":{"ru_utime":{"tv_sec":6,"tv_usec":731765},"ru_stime":{"tv_sec":0,"tv_usec":247786},"ru_maxrss":134084,"ru_ixrss":0,"ru_idrss":0,"ru_isrss":0,"ru_minflt":62314,"ru_majflt":0,"ru_nswap":0,"ru_inblock":0,"ru_oublock":0,"ru_msgsnd":0,"ru_msgrcv":0,"ru_nsignals":0,"ru_nvcsw":562,"ru_nivcsw":1135}}
{"runtime":6927,"energy":{"pkg":130.0704345703125,"pp0":0,"dram":33.8323974609375},"rusage":{"ru_utime":{"tv_sec":6,"tv_usec":567981},"ru_stime":{"tv_sec":0,"tv_usec":236921},"ru_maxrss":134136,"ru_ixrss":0,"ru_idrss":0,"ru_isrss":0,"ru_minflt":60666,"ru_majflt":0,"ru_nswap":0,"ru_inblock":0,"ru_oublock":0,"ru_msgsnd":0,"ru_msgrcv":0,"ru_nsignals":0,"ru_nvcsw":749,"ru_nivcsw":1128}}
{"runtime":7066,"energy":{"pkg":130.02783203125,"pp0":0,"dram":33.787353515625},"rusage":{"ru_utime":{"tv_sec":6,"tv_usec":637266},"ru_stime":{"tv_sec":0,"tv_usec":295464},"ru_maxrss":134188,"ru_ixrss":0,"ru_idrss":0,"ru_isrss":0,"ru_minflt":60669,"ru_majflt":0,"ru_nswap":0,"ru_inblock":0,"ru_oublock":0,"ru_msgsnd":0,"ru_msgrcv":0,"ru_nsignals":0,"ru_nvcsw":877,"ru_nivcsw":1147}}
{"runtime":7566,"energy":{"pkg":135.4749755859375,"pp0":0,"dram":36.88446044921875},"rusage":{"ru_utime":{"tv_sec":7,"tv_usec":220404},"ru_stime":{"tv_sec":0,"tv_usec":286693},"ru_maxrss":134032,"ru_ixrss":0,"ru_idrss":0,"ru_isrss":0,"ru_minflt":69899,"ru_majflt":0,"ru_nswap":0,"ru_inblock":0,"ru_oublock":0,"ru_msgsnd":0,"ru_msgrcv":0,"ru_nsignals":0,"ru_nvcsw":812,"ru_nivcsw":1245}}
{"runtime":7206,"energy":{"pkg":131.5994873046875,"pp0":0,"dram":34.35009765625},"rusage":{"ru_utime":{"tv_sec":6,"tv_usec":862706},"ru_stime":{"tv_sec":0,"tv_usec":280545},"ru_maxrss":134068,"ru_ixrss":0,"ru_idrss":0,"ru_isrss":0,"ru_minflt":69214,"ru_majflt":0,"ru_nswap":0,"ru_inblock":0,"ru_oublock":0,"ru_msgsnd":0,"ru_msgrcv":0,"ru_nsignals":0,"ru_nvcsw":809,"ru_nivcsw":1097}}
{"runtime":7231,"energy":{"pkg":130.21478271484375,"pp0":0,"dram":33.4267578125},"rusage":{"ru_utime":{"tv_sec":6,"tv_usec":808785},"ru_stime":{"tv_sec":0,"tv_usec":291123},"ru_maxrss":134076,"ru_ixrss":0,"ru_idrss":0,"ru_isrss":0,"ru_minflt":60665,"ru_majflt":0,"ru_nswap":0,"ru_inblock":0,"ru_oublock":0,"ru_msgsnd":0,"ru_msgrcv":0,"ru_nsignals":0,"ru_nvcsw":774,"ru_nivcsw":1151}}
{"runtime":7073,"energy":{"pkg":128.8760986328125,"pp0":0,"dram":33.41204833984375},"rusage":{"ru_utime":{"tv_sec":6,"tv_usec":728291},"ru_stime":{"tv_sec":0,"tv_usec":264430},"ru_maxrss":134112,"ru_ixrss":0,"ru_idrss":0,"ru_isrss":0,"ru_minflt":60664,"ru_majflt":0,"ru_nswap":0,"ru_inblock":0,"ru_oublock":0,"ru_msgsnd":0,"ru_msgrcv":0,"ru_nsignals":0,"ru_nvcsw":789,"ru_nivcsw":1075}}
{"runtime":7316,"energy":{"pkg":133.48822021484375,"pp0":0,"dram":33.96356201171875},"rusage":{"ru_utime":{"tv_sec":6,"tv_usec":891735},"ru_stime":{"tv_sec":0,"tv_usec":278480},"ru_maxrss":134104,"ru_ixrss":0,"ru_idrss":0,"ru_isrss":0,"ru_minflt":60668,"ru_majflt":0,"ru_nswap":0,"ru_inblock":0,"ru_oublock":0,"ru_msgsnd":0,"ru_msgrcv":0,"ru_nsignals":0,"ru_nvcsw":1423,"ru_nivcsw":1129}}
{"runtime":7168,"energy":{"pkg":130.3299560546875,"pp0":0,"dram":33.63134765625},"rusage":{"ru_utime":{"tv_sec":6,"tv_usec":818471},"ru_stime":{"tv_sec":0,"tv_usec":238917},"ru_maxrss":134144,"ru_ixrss":0,"ru_idrss":0,"ru_isrss":0,"ru_minflt":60667,"ru_majflt":0,"ru_nswap":0,"ru_inblock":0,"ru_oublock":0,"ru_msgsnd":0,"ru_msgrcv":0,"ru_nsignals":0,"ru_nvcsw":776,"ru_nivcsw":1173}}
{"runtime":7275,"energy":{"pkg":132.40093994140625,"pp0":0,"dram":34.09466552734375},"rusage":{"ru_utime":{"tv_sec":6,"tv_usec":904633},"ru_stime":{"tv_sec":0,"tv_usec":284703},"ru_maxrss":134132,"ru_ixrss":0,"ru_idrss":0,"ru_isrss":0,"ru_minflt":60667,"ru_majflt":0,"ru_nswap":0,"ru_inblock":0,"ru_oublock":0,"ru_msgsnd":0,"ru_msgrcv":0,"ru_nsignals":0,"ru_nvcsw":922,"ru_nivcsw":1125}}
