{"runtime":3002,"energy":{"pkg":265.703857421875,"pp0":0,"dram":28.9351806640625},"rusage":{"ru_utime":{"tv_sec":86,"tv_usec":33960},"ru_stime":{"tv_sec":0,"tv_usec":179991},"ru_maxrss":47316,"ru_ixrss":0,"ru_idrss":0,"ru_isrss":0,"ru_minflt":8724,"ru_majflt":14,"ru_nswap":0,"ru_inblock":0,"ru_oublock":96,"ru_msgsnd":0,"ru_msgrcv":0,"ru_nsignals":0,"ru_nvcsw":1847,"ru_nivcsw":9868}}
{"runtime":3141,"energy":{"pkg":266.63916015625,"pp0":0,"dram":29.67059326171875},"rusage":{"ru_utime":{"tv_sec":83,"tv_usec":867110},"ru_stime":{"tv_sec":0,"tv_usec":48026},"ru_maxrss":47492,"ru_ixrss":0,"ru_idrss":0,"ru_isrss":0,"ru_minflt":8495,"ru_majflt":11,"ru_nswap":0,"ru_inblock":0,"ru_oublock":88,"ru_msgsnd":0,"ru_msgrcv":0,"ru_nsignals":0,"ru_nvcsw":1858,"ru_nivcsw":9495}}
{"runtime":2938,"energy":{"pkg":259.9744873046875,"pp0":0,"dram":28.64215087890625},"rusage":{"ru_utime":{"tv_sec":84,"tv_usec":153962},"ru_stime":{"tv_sec":0,"tv_usec":195899},"ru_maxrss":47644,"ru_ixrss":0,"ru_idrss":0,"ru_isrss":0,"ru_minflt":8681,"ru_majflt":8,"ru_nswap":0,"ru_inblock":0,"ru_oublock":64,"ru_msgsnd":0,"ru_msgrcv":0,"ru_nsignals":0,"ru_nvcsw":1777,"ru_nivcsw":10338}}
{"runtime":3123,"energy":{"pkg":271.337646484375,"pp0":0,"dram":29.402587890625},"rusage":{"ru_utime":{"tv_sec":85,"tv_usec":645571},"ru_stime":{"tv_sec":0,"tv_usec":76085},"ru_maxrss":47460,"ru_ixrss":0,"ru_idrss":0,"ru_isrss":0,"ru_minflt":8573,"ru_majflt":18,"ru_nswap":0,"ru_inblock":0,"ru_oublock":96,"ru_msgsnd":0,"ru_msgrcv":0,"ru_nsignals":0,"ru_nvcsw":1701,"ru_nivcsw":10527}}
{"runtime":3103,"energy":{"pkg":268.54315185546875,"pp0":0,"dram":29.3326416015625},"rusage":{"ru_utime":{"tv_sec":85,"tv_usec":86591},"ru_stime":{"tv_sec":0,"tv_usec":67854},"ru_maxrss":47152,"ru_ixrss":0,"ru_idrss":0,"ru_isrss":0,"ru_minflt":8499,"ru_majflt":8,"ru_nswap":0,"ru_inblock":0,"ru_oublock":64,"ru_msgsnd":0,"ru_msgrcv":0,"ru_nsignals":0,"ru_nvcsw":1699,"ru_nivcsw":9972}}
{"runtime":2910,"energy":{"pkg":258.67559814453125,"pp0":0,"dram":28.4127197265625},"rusage":{"ru_utime":{"tv_sec":82,"tv_usec":771667},"ru_stime":{"tv_sec":0,"tv_usec":48003},"ru_maxrss":47108,"ru_ixrss":0,"ru_idrss":0,"ru_isrss":0,"ru_minflt":8448,"ru_majflt":12,"ru_nswap":0,"ru_inblock":0,"ru_oublock":96,"ru_msgsnd":0,"ru_msgrcv":0,"ru_nsignals":0,"ru_nvcsw":1845,"ru_nivcsw":10111}}
{"runtime":3079,"energy":{"pkg":269.48095703125,"pp0":0,"dram":29.73675537109375},"rusage":{"ru_utime":{"tv_sec":84,"tv_usec":646479},"ru_stime":{"tv_sec":0,"tv_usec":47919},"ru_maxrss":47916,"ru_ixrss":0,"ru_idrss":0,"ru_isrss":0,"ru_minflt":8584,"ru_majflt":32,"ru_nswap":0,"ru_inblock":0,"ru_oublock":96,"ru_msgsnd":0,"ru_msgrcv":0,"ru_nsignals":0,"ru_nvcsw":1936,"ru_nivcsw":10358}}
{"runtime":3010,"energy":{"pkg":268.07574462890625,"pp0":0,"dram":29.23291015625},"rusage":{"ru_utime":{"tv_sec":85,"tv_usec":664672},"ru_stime":{"tv_sec":0,"tv_usec":57475},"ru_maxrss":47472,"ru_ixrss":0,"ru_idrss":0,"ru_isrss":0,"ru_minflt":8786,"ru_majflt":8,"ru_nswap":0,"ru_inblock":0,"ru_oublock":64,"ru_msgsnd":0,"ru_msgrcv":0,"ru_nsignals":0,"ru_nvcsw":1800,"ru_nivcsw":9039}}
{"runtime":3060,"energy":{"pkg":266.41558837890625,"pp0":0,"dram":29.24578857421875},"rusage":{"ru_utime":{"tv_sec":83,"tv_usec":368321},"ru_stime":{"tv_sec":0,"tv_usec":44056},"ru_maxrss":47200,"ru_ixrss":0,"ru_idrss":0,"ru_isrss":0,"ru_minflt":8562,"ru_majflt":12,"ru_nswap":0,"ru_inblock":0,"ru_oublock":96,"ru_msgsnd":0,"ru_msgrcv":0,"ru_nsignals":0,"ru_nvcsw":1933,"ru_nivcsw":9830}}
{"runtime":3139,"energy":{"pkg":271.4381103515625,"pp0":0,"dram":30.3677978515625},"rusage":{"ru_utime":{"tv_sec":85,"tv_usec":195393},"ru_stime":{"tv_sec":0,"tv_usec":48012},"ru_maxrss":47732,"ru_ixrss":0,"ru_idrss":0,"ru_isrss":0,"ru_minflt":8570,"ru_majflt":8,"ru_nswap":0,"ru_inblock":0,"ru_oublock":64,"ru_msgsnd":0,"ru_msgrcv":0,"ru_nsignals":0,"ru_nvcsw":1829,"ru_nivcsw":10557}}
{"runtime":3140,"energy":{"pkg":272.21881103515625,"pp0":0,"dram":30.72064208984375},"rusage":{"ru_utime":{"tv_sec":84,"tv_usec":47805},"ru_stime":{"tv_sec":0,"tv_usec":57269},"ru_maxrss":47748,"ru_ixrss":0,"ru_idrss":0,"ru_isrss":0,"ru_minflt":8722,"ru_majflt":12,"ru_nswap":0,"ru_inblock":0,"ru_oublock":96,"ru_msgsnd":0,"ru_msgrcv":0,"ru_nsignals":0,"ru_nvcsw":1889,"ru_nivcsw":10347}}
{"runtime":3140,"energy":{"pkg":271.50201416015625,"pp0":0,"dram":30.15277099609375},"rusage":{"ru_utime":{"tv_sec":84,"tv_usec":946813},"ru_stime":{"tv_sec":0,"tv_usec":88271},"ru_maxrss":47544,"ru_ixrss":0,"ru_idrss":0,"ru_isrss":0,"ru_minflt":8543,"ru_majflt":24,"ru_nswap":0,"ru_inblock":0,"ru_oublock":96,"ru_msgsnd":0,"ru_msgrcv":0,"ru_nsignals":0,"ru_nvcsw":1961,"ru_nivcsw":10469}}
{"runtime":2892,"energy":{"pkg":259.476806640625,"pp0":0,"dram":28.4354248046875},"rusage":{"ru_utime":{"tv_sec":82,"tv_usec":771853},"ru_stime":{"tv_sec":0,"tv_usec":32011},"ru_maxrss":47452,"ru_ixrss":0,"ru_idrss":0,"ru_isrss":0,"ru_minflt":8548,"ru_majflt":8,"ru_nswap":0,"ru_inblock":0,"ru_oublock":64,"ru_msgsnd":0,"ru_msgrcv":0,"ru_nsignals":0,"ru_nvcsw":1886,"ru_nivcsw":9404}}
{"runtime":3105,"energy":{"pkg":272.9097900390625,"pp0":0,"dram":30.10235595703125},"rusage":{"ru_utime":{"tv_sec":85,"tv_usec":252802},"ru_stime":{"tv_sec":0,"tv_usec":40018},"ru_maxrss":47128,"ru_ixrss":0,"ru_idrss":0,"ru_isrss":0,"ru_minflt":8550,"ru_majflt":14,"ru_nswap":0,"ru_inblock":0,"ru_oublock":96,"ru_msgsnd":0,"ru_msgrcv":0,"ru_nsignals":0,"ru_nvcsw":1805,"ru_nivcsw":10346}}
{"runtime":2970,"energy":{"pkg":265.3798828125,"pp0":0,"dram":28.76953125},"rusage":{"ru_utime":{"tv_sec":84,"tv_usec":933190},"ru_stime":{"tv_sec":0,"tv_usec":87995},"ru_maxrss":47592,"ru_ixrss":0,"ru_idrss":0,"ru_isrss":0,"ru_minflt":8531,"ru_majflt":17,"ru_nswap":0,"ru_inblock":0,"ru_oublock":64,"ru_msgsnd":0,"ru_msgrcv":0,"ru_nsignals":0,"ru_nvcsw":1777,"ru_nivcsw":10294}}
{"runtime":3153,"energy":{"pkg":274.40679931640625,"pp0":0,"dram":31.20361328125},"rusage":{"ru_utime":{"tv_sec":85,"tv_usec":525222},"ru_stime":{"tv_sec":0,"tv_usec":85106},"ru_maxrss":47576,"ru_ixrss":0,"ru_idrss":0,"ru_isrss":0,"ru_minflt":8596,"ru_majflt":24,"ru_nswap":0,"ru_inblock":0,"ru_oublock":96,"ru_msgsnd":0,"ru_msgrcv":0,"ru_nsignals":0,"ru_nvcsw":1745,"ru_nivcsw":10680}}
{"runtime":3096,"energy":{"pkg":269.71661376953125,"pp0":0,"dram":29.90130615234375},"rusage":{"ru_utime":{"tv_sec":84,"tv_usec":503678},"ru_stime":{"tv_sec":0,"tv_usec":52070},"ru_maxrss":47748,"ru_ixrss":0,"ru_idrss":0,"ru_isrss":0,"ru_minflt":8699,"ru_majflt":12,"ru_nswap":0,"ru_inblock":0,"ru_oublock":96,"ru_msgsnd":0,"ru_msgrcv":0,"ru_nsignals":0,"ru_nvcsw":1792,"ru_nivcsw":10255}}
{"runtime":2962,"energy":{"pkg":262.36798095703125,"pp0":0,"dram":28.98809814453125},"rusage":{"ru_utime":{"tv_sec":83,"tv_usec":907955},"ru_stime":{"tv_sec":0,"tv_usec":151701},"ru_maxrss":47212,"ru_ixrss":0,"ru_idrss":0,"ru_isrss":0,"ru_minflt":8639,"ru_majflt":8,"ru_nswap":0,"ru_inblock":0,"ru_oublock":64,"ru_msgsnd":0,"ru_msgrcv":0,"ru_nsignals":0,"ru_nvcsw":1758,"ru_nivcsw":10381}}
{"runtime":3006,"energy":{"pkg":265.75714111328125,"pp0":0,"dram":29.61212158203125},"rusage":{"ru_utime":{"tv_sec":86,"tv_usec":39306},"ru_stime":{"tv_sec":0,"tv_usec":72028},"ru_maxrss":47648,"ru_ixrss":0,"ru_idrss":0,"ru_isrss":0,"ru_minflt":8697,"ru_majflt":37,"ru_nswap":0,"ru_inblock":0,"ru_oublock":96,"ru_msgsnd":0,"ru_msgrcv":0,"ru_nsignals":0,"ru_nvcsw":1701,"ru_nivcsw":10702}}
{"runtime":2937,"energy":{"pkg":261.7591552734375,"pp0":0,"dram":28.9171142578125},"rusage":{"ru_utime":{"tv_sec":83,"tv_usec":678873},"ru_stime":{"tv_sec":0,"tv_usec":72004},"ru_maxrss":47072,"ru_ixrss":0,"ru_idrss":0,"ru_isrss":0,"ru_minflt":8459,"ru_majflt":15,"ru_nswap":0,"ru_inblock":0,"ru_oublock":64,"ru_msgsnd":0,"ru_msgrcv":0,"ru_nsignals":0,"ru_nvcsw":1746,"ru_nivcsw":10235}}
{"runtime":3122,"energy":{"pkg":271.189453125,"pp0":0,"dram":30.0924072265625},"rusage":{"ru_utime":{"tv_sec":84,"tv_usec":923297},"ru_stime":{"tv_sec":0,"tv_usec":79956},"ru_maxrss":46992,"ru_ixrss":0,"ru_idrss":0,"ru_isrss":0,"ru_minflt":8546,"ru_majflt":23,"ru_nswap":0,"ru_inblock":0,"ru_oublock":96,"ru_msgsnd":0,"ru_msgrcv":0,"ru_nsignals":0,"ru_nvcsw":1825,"ru_nivcsw":10242}}
