{"runtime":2944,"energy":{"pkg":229.13323974609375,"pp0":0,"dram":26.689208984375},"perf_counters":{"PERF_COUNT_HW_REF_CPU_CYCLES":0,"PERF_COUNT_HW_BRANCH_INSTRUCTIONS":0,"PERF_COUNT_HW_CACHE_MISSES":0,"PERF_COUNT_HW_INSTRUCTIONS":0,"PERF_COUNT_HW_BRANCH_MISSES":0,"PERF_COUNT_HW_CACHE_REFERENCES":0,"PERF_COUNT_HW_CPU_CYCLES":0}}
{"runtime":2764,"energy":{"pkg":223.96600341796875,"pp0":0,"dram":25.27001953125},"perf_counters":{"PERF_COUNT_HW_REF_CPU_CYCLES":0,"PERF_COUNT_HW_BRANCH_INSTRUCTIONS":0,"PERF_COUNT_HW_CACHE_MISSES":0,"PERF_COUNT_HW_INSTRUCTIONS":0,"PERF_COUNT_HW_BRANCH_MISSES":0,"PERF_COUNT_HW_CACHE_REFERENCES":0,"PERF_COUNT_HW_CPU_CYCLES":0}}
{"runtime":3224,"energy":{"pkg":241.1610107421875,"pp0":0,"dram":29.57647705078125},"perf_counters":{"PERF_COUNT_HW_REF_CPU_CYCLES":0,"PERF_COUNT_HW_BRANCH_INSTRUCTIONS":0,"PERF_COUNT_HW_CACHE_MISSES":0,"PERF_COUNT_HW_INSTRUCTIONS":0,"PERF_COUNT_HW_BRANCH_MISSES":0,"PERF_COUNT_HW_CACHE_REFERENCES":0,"PERF_COUNT_HW_CPU_CYCLES":0}}
{"runtime":2866,"energy":{"pkg":227.7467041015625,"pp0":0,"dram":26.14947509765625},"perf_counters":{"PERF_COUNT_HW_REF_CPU_CYCLES":0,"PERF_COUNT_HW_BRANCH_INSTRUCTIONS":0,"PERF_COUNT_HW_CACHE_MISSES":0,"PERF_COUNT_HW_INSTRUCTIONS":0,"PERF_COUNT_HW_BRANCH_MISSES":0,"PERF_COUNT_HW_CACHE_REFERENCES":0,"PERF_COUNT_HW_CPU_CYCLES":0}}
{"runtime":2815,"energy":{"pkg":225.263427734375,"pp0":0,"dram":25.79046630859375},"perf_counters":{"PERF_COUNT_HW_REF_CPU_CYCLES":0,"PERF_COUNT_HW_BRANCH_INSTRUCTIONS":0,"PERF_COUNT_HW_CACHE_MISSES":0,"PERF_COUNT_HW_INSTRUCTIONS":0,"PERF_COUNT_HW_BRANCH_MISSES":0,"PERF_COUNT_HW_CACHE_REFERENCES":0,"PERF_COUNT_HW_CPU_CYCLES":0}}
{"runtime":2789,"energy":{"pkg":226.7117919921875,"pp0":0,"dram":25.41400146484375},"perf_counters":{"PERF_COUNT_HW_REF_CPU_CYCLES":0,"PERF_COUNT_HW_BRANCH_INSTRUCTIONS":0,"PERF_COUNT_HW_CACHE_MISSES":0,"PERF_COUNT_HW_INSTRUCTIONS":0,"PERF_COUNT_HW_BRANCH_MISSES":0,"PERF_COUNT_HW_CACHE_REFERENCES":0,"PERF_COUNT_HW_CPU_CYCLES":0}}
{"runtime":3224,"energy":{"pkg":244.25732421875,"pp0":0,"dram":29.46270751953125},"perf_counters":{"PERF_COUNT_HW_REF_CPU_CYCLES":0,"PERF_COUNT_HW_BRANCH_INSTRUCTIONS":0,"PERF_COUNT_HW_CACHE_MISSES":0,"PERF_COUNT_HW_INSTRUCTIONS":0,"PERF_COUNT_HW_BRANCH_MISSES":0,"PERF_COUNT_HW_CACHE_REFERENCES":0,"PERF_COUNT_HW_CPU_CYCLES":0}}
{"runtime":2871,"energy":{"pkg":229.42724609375,"pp0":0,"dram":26.125},"perf_counters":{"PERF_COUNT_HW_REF_CPU_CYCLES":0,"PERF_COUNT_HW_BRANCH_INSTRUCTIONS":0,"PERF_COUNT_HW_CACHE_MISSES":0,"PERF_COUNT_HW_INSTRUCTIONS":0,"PERF_COUNT_HW_BRANCH_MISSES":0,"PERF_COUNT_HW_CACHE_REFERENCES":0,"PERF_COUNT_HW_CPU_CYCLES":0}}
{"runtime":3388,"energy":{"pkg":241.86895751953125,"pp0":0,"dram":29.9637451171875},"perf_counters":{"PERF_COUNT_HW_REF_CPU_CYCLES":0,"PERF_COUNT_HW_BRANCH_INSTRUCTIONS":0,"PERF_COUNT_HW_CACHE_MISSES":0,"PERF_COUNT_HW_INSTRUCTIONS":0,"PERF_COUNT_HW_BRANCH_MISSES":0,"PERF_COUNT_HW_CACHE_REFERENCES":0,"PERF_COUNT_HW_CPU_CYCLES":0}}
{"runtime":2871,"energy":{"pkg":228.63299560546875,"pp0":0,"dram":26.2554931640625},"perf_counters":{"PERF_COUNT_HW_REF_CPU_CYCLES":0,"PERF_COUNT_HW_BRANCH_INSTRUCTIONS":0,"PERF_COUNT_HW_CACHE_MISSES":0,"PERF_COUNT_HW_INSTRUCTIONS":0,"PERF_COUNT_HW_BRANCH_MISSES":0,"PERF_COUNT_HW_CACHE_REFERENCES":0,"PERF_COUNT_HW_CPU_CYCLES":0}}
{"runtime":2813,"energy":{"pkg":227.03570556640625,"pp0":0,"dram":25.88690185546875},"perf_counters":{"PERF_COUNT_HW_REF_CPU_CYCLES":0,"PERF_COUNT_HW_BRANCH_INSTRUCTIONS":0,"PERF_COUNT_HW_CACHE_MISSES":0,"PERF_COUNT_HW_INSTRUCTIONS":0,"PERF_COUNT_HW_BRANCH_MISSES":0,"PERF_COUNT_HW_CACHE_REFERENCES":0,"PERF_COUNT_HW_CPU_CYCLES":0}}
{"runtime":2788,"energy":{"pkg":228.3323974609375,"pp0":0,"dram":25.43206787109375},"perf_counters":{"PERF_COUNT_HW_REF_CPU_CYCLES":0,"PERF_COUNT_HW_BRANCH_INSTRUCTIONS":0,"PERF_COUNT_HW_CACHE_MISSES":0,"PERF_COUNT_HW_INSTRUCTIONS":0,"PERF_COUNT_HW_BRANCH_MISSES":0,"PERF_COUNT_HW_CACHE_REFERENCES":0,"PERF_COUNT_HW_CPU_CYCLES":0}}
{"runtime":3073,"energy":{"pkg":237.71917724609375,"pp0":0,"dram":28.05999755859375},"perf_counters":{"PERF_COUNT_HW_REF_CPU_CYCLES":0,"PERF_COUNT_HW_BRANCH_INSTRUCTIONS":0,"PERF_COUNT_HW_CACHE_MISSES":0,"PERF_COUNT_HW_INSTRUCTIONS":0,"PERF_COUNT_HW_BRANCH_MISSES":0,"PERF_COUNT_HW_CACHE_REFERENCES":0,"PERF_COUNT_HW_CPU_CYCLES":0}}
{"runtime":2781,"energy":{"pkg":229.2596435546875,"pp0":0,"dram":25.786376953125},"perf_counters":{"PERF_COUNT_HW_REF_CPU_CYCLES":0,"PERF_COUNT_HW_BRANCH_INSTRUCTIONS":0,"PERF_COUNT_HW_CACHE_MISSES":0,"PERF_COUNT_HW_INSTRUCTIONS":0,"PERF_COUNT_HW_BRANCH_MISSES":0,"PERF_COUNT_HW_CACHE_REFERENCES":0,"PERF_COUNT_HW_CPU_CYCLES":0}}
{"runtime":3258,"energy":{"pkg":246.0921630859375,"pp0":0,"dram":30.29083251953125},"perf_counters":{"PERF_COUNT_HW_REF_CPU_CYCLES":0,"PERF_COUNT_HW_BRANCH_INSTRUCTIONS":0,"PERF_COUNT_HW_CACHE_MISSES":0,"PERF_COUNT_HW_INSTRUCTIONS":0,"PERF_COUNT_HW_BRANCH_MISSES":0,"PERF_COUNT_HW_CACHE_REFERENCES":0,"PERF_COUNT_HW_CPU_CYCLES":0}}
{"runtime":2840,"energy":{"pkg":231.33416748046875,"pp0":0,"dram":26.1630859375},"perf_counters":{"PERF_COUNT_HW_REF_CPU_CYCLES":0,"PERF_COUNT_HW_BRANCH_INSTRUCTIONS":0,"PERF_COUNT_HW_CACHE_MISSES":0,"PERF_COUNT_HW_INSTRUCTIONS":0,"PERF_COUNT_HW_BRANCH_MISSES":0,"PERF_COUNT_HW_CACHE_REFERENCES":0,"PERF_COUNT_HW_CPU_CYCLES":0}}
{"runtime":2821,"energy":{"pkg":229.50531005859375,"pp0":0,"dram":26.00146484375},"perf_counters":{"PERF_COUNT_HW_REF_CPU_CYCLES":0,"PERF_COUNT_HW_BRANCH_INSTRUCTIONS":0,"PERF_COUNT_HW_CACHE_MISSES":0,"PERF_COUNT_HW_INSTRUCTIONS":0,"PERF_COUNT_HW_BRANCH_MISSES":0,"PERF_COUNT_HW_CACHE_REFERENCES":0,"PERF_COUNT_HW_CPU_CYCLES":0}}
{"runtime":2796,"energy":{"pkg":231.97442626953125,"pp0":0,"dram":25.88897705078125},"perf_counters":{"PERF_COUNT_HW_REF_CPU_CYCLES":0,"PERF_COUNT_HW_BRANCH_INSTRUCTIONS":0,"PERF_COUNT_HW_CACHE_MISSES":0,"PERF_COUNT_HW_INSTRUCTIONS":0,"PERF_COUNT_HW_BRANCH_MISSES":0,"PERF_COUNT_HW_CACHE_REFERENCES":0,"PERF_COUNT_HW_CPU_CYCLES":0}}
{"runtime":3122,"energy":{"pkg":241.81634521484375,"pp0":0,"dram":28.787353515625},"perf_counters":{"PERF_COUNT_HW_REF_CPU_CYCLES":0,"PERF_COUNT_HW_BRANCH_INSTRUCTIONS":0,"PERF_COUNT_HW_CACHE_MISSES":0,"PERF_COUNT_HW_INSTRUCTIONS":0,"PERF_COUNT_HW_BRANCH_MISSES":0,"PERF_COUNT_HW_CACHE_REFERENCES":0,"PERF_COUNT_HW_CPU_CYCLES":0}}
{"runtime":2806,"energy":{"pkg":231.27191162109375,"pp0":0,"dram":25.92730712890625},"perf_counters":{"PERF_COUNT_HW_REF_CPU_CYCLES":0,"PERF_COUNT_HW_BRANCH_INSTRUCTIONS":0,"PERF_COUNT_HW_CACHE_MISSES":0,"PERF_COUNT_HW_INSTRUCTIONS":0,"PERF_COUNT_HW_BRANCH_MISSES":0,"PERF_COUNT_HW_CACHE_REFERENCES":0,"PERF_COUNT_HW_CPU_CYCLES":0}}
{"runtime":3090,"energy":{"pkg":240.4019775390625,"pp0":0,"dram":28.085693359375},"perf_counters":{"PERF_COUNT_HW_REF_CPU_CYCLES":0,"PERF_COUNT_HW_BRANCH_INSTRUCTIONS":0,"PERF_COUNT_HW_CACHE_MISSES":0,"PERF_COUNT_HW_INSTRUCTIONS":0,"PERF_COUNT_HW_BRANCH_MISSES":0,"PERF_COUNT_HW_CACHE_REFERENCES":0,"PERF_COUNT_HW_CPU_CYCLES":0}}
